pyosis/__init__.py
pyosis/_generate_models.py
pyosis/py.typed
pyosis/serialization.py
pyosis/generated/__init__.py
pyosis/generated/osis_core_2_1_1.py
pyosis/generated/xml.py
pyosis-0.2.1.dist-info/licenses/LICENSE
pyosis-0.2.1.dist-info/METADATA
pyosis-0.2.1.dist-info/WHEEL
pyosis-0.2.1.dist-info/top_level.txt
pyosis-0.2.1.dist-info/RECORD
