Metadata-Version: 2.4
Name: pyosis
Version: 0.2.1
Summary: Unofficial Python client for parsing OSIS (Open Scriptural Information Standard) files
Author-email: "Andrew P. Sansom" <andrew@euleriancircuit.com>
License: MIT License
Project-URL: Documentation, https://pyosis.readthedocs.io/en/stable/
Project-URL: Homepage, https://github.com/open-canon/pyosis
Project-URL: Issues, https://github.com/open-canon/pyosis/issues
Project-URL: Repository, https://github.com/open-canon/pyosis.git
Keywords: bible study,bible tools,bible,data parsing,digital humanities,digital scripture,open scripture,osis parser,osis,parser,pypi,python,religious texts,scripture analysis,scripture parser,scripture,text analytics,text processing,xml parsing,xml
Classifier: Development Status :: 2 - Pre-Alpha
Classifier: Intended Audience :: Developers
Classifier: Intended Audience :: Religion
Classifier: License :: OSI Approved :: MIT License
Classifier: Programming Language :: Python :: 3
Classifier: Programming Language :: Python :: 3.10
Classifier: Programming Language :: Python :: 3.11
Classifier: Programming Language :: Python :: 3.12
Classifier: Programming Language :: Python :: 3.9
Classifier: Programming Language :: Python
Classifier: Topic :: Religion
Requires-Python: >=3.9
License-File: LICENSE
Requires-Dist: pydantic<=2.10.4,>2.0.0
Requires-Dist: pydantic_extra_types[pycountry]==2.10.4
Requires-Dist: xsdata-pydantic==24.5
Requires-Dist: xsdata==25.7
Provides-Extra: dev
Requires-Dist: hypothesis==6.123.14; extra == "dev"
Requires-Dist: mypy==1.14.1; extra == "dev"
Requires-Dist: pyright==1.1.391; extra == "dev"
Requires-Dist: pytest-cov==6.0.0; extra == "dev"
Requires-Dist: pytest-github-actions-annotate-failures; extra == "dev"
Requires-Dist: pytest==8.3.4; extra == "dev"
Requires-Dist: ruff==0.8.6; extra == "dev"
Requires-Dist: toml-sort==0.24.2; extra == "dev"
Provides-Extra: docs
Requires-Dist: mkdocs-autolinks-plugin==0.7.1; extra == "docs"
Requires-Dist: mkdocs-exclude==1.0.2; extra == "docs"
Requires-Dist: mkdocs-material==9.5.49; extra == "docs"
Requires-Dist: mkdocs-snippets==1.3.0; extra == "docs"
Requires-Dist: mkdocs==1.6.1; extra == "docs"
Requires-Dist: mkdocstrings[python]==0.27.0; extra == "docs"
Dynamic: license-file
